radicale_storage_family_scheduler/__init__.py
radicale_storage_family_scheduler-0.0.1.dist-info/DESCRIPTION.rst
radicale_storage_family_scheduler-0.0.1.dist-info/METADATA
radicale_storage_family_scheduler-0.0.1.dist-info/RECORD
radicale_storage_family_scheduler-0.0.1.dist-info/WHEEL
radicale_storage_family_scheduler-0.0.1.dist-info/metadata.json
radicale_storage_family_scheduler-0.0.1.dist-info/top_level.txt
