Metadata-Version: 2.0
Name: radicale-storage-family-scheduler
Version: 0.0.1
Summary: Basic scheduling for users on the same server
Home-page: https://github.com/ialokim/radicale_storage_family_scheduler
Author: ialokim
Author-email: UNKNOWN
License: GPLv3
Keywords: radicale storage scheduling caldav python
Platform: UNKNOWN
Requires-Dist: radicale
